uncertainty/__init__.py
uncertainty/result.py
uncertainty/sbool.py
uncertainty/ubool.py
uncertainty/uenum.py
uncertainty/unumbers.py
uncertainty/ustr.py
uncertainty/utypes.py
uncertainty_datatypes-1.1.5.dist-info/LICENSE
uncertainty_datatypes-1.1.5.dist-info/METADATA
uncertainty_datatypes-1.1.5.dist-info/WHEEL
uncertainty_datatypes-1.1.5.dist-info/top_level.txt
uncertainty_datatypes-1.1.5.dist-info/RECORD
