Metadata-Version: 2.1
Name: uncertainty-datatypes
Version: 1.1.5
Summary: Uncertainty Datatypes Library
Author: Atenea Research Group, University of Malaga, Spain
Project-URL: Homepage, https://atenea.lcc.uma.es
Project-URL: Repository, https://github.com/atenearesearchgroup/uncertainty-datatypes-python
Project-URL: Bug Tracker, https://github.com/atenearesearchgroup/uncertainty/issues
Classifier: Intended Audience :: Science/Research
Classifier: Intended Audience :: Developers
Classifier: Intended Audience :: Education
Classifier: Operating System :: OS Independent
Classifier: Programming Language :: Python :: 3.11
Classifier: Topic :: Education
Classifier: Topic :: Software Development
Classifier: Topic :: Software Development :: Libraries
Requires-Python: >=3.11
License-File: LICENSE
Requires-Dist: numpy >=1.25.0
